opentelemetry/instrumentation/replicate/__init__.py
opentelemetry/instrumentation/replicate/config.py
opentelemetry/instrumentation/replicate/event_emitter.py
opentelemetry/instrumentation/replicate/event_models.py
opentelemetry/instrumentation/replicate/span_utils.py
opentelemetry/instrumentation/replicate/utils.py
opentelemetry/instrumentation/replicate/version.py
opentelemetry_instrumentation_replicate-0.51.1.dist-info/METADATA
opentelemetry_instrumentation_replicate-0.51.1.dist-info/WHEEL
opentelemetry_instrumentation_replicate-0.51.1.dist-info/entry_points.txt
opentelemetry_instrumentation_replicate-0.51.1.dist-info/RECORD
