Metadata-Version: 2.4
Name: opentelemetry-instrumentation-replicate
Version: 0.51.1
Summary: OpenTelemetry Replicate instrumentation
Project-URL: Repository, https://github.com/traceloop/openllmetry/tree/main/packages/opentelemetry-instrumentation-replicate
Author-email: Kartik Prajapati <kartik@ktklab.org>
License-Expression: Apache-2.0
Requires-Python: <4,>=3.10
Requires-Dist: opentelemetry-api<2,>=1.38.0
Requires-Dist: opentelemetry-instrumentation>=0.59b0
Requires-Dist: opentelemetry-semantic-conventions-ai<0.5.0,>=0.4.13
Requires-Dist: opentelemetry-semantic-conventions>=0.59b0
Provides-Extra: instruments
Requires-Dist: replicate; extra == 'instruments'
